<?xml version="1.0" encoding="utf-8"?>
<QuestData xmlns:xsi="http://www.w3.org/2001/XMLSchema-instance" xmlns:xsd="http://www.w3.org/2001/XMLSchema" id="9794">
  <Title>No Time for Curiosity</Title>
  <Description>$n, I have a favor to ask of you. Normally, I would do this myself, but my hands are already beyond full.$B$BI have an associate named Kialon at Sylvanaar in the Blade's Edge Mountains to the north. He's expecting to hear from me in the near future, although I suspect he won't like what I have to say.$B$BIf you would deliver my response to him, you would have my gratitude. I must insist, and this is very important, that you not attempt to read the letter. It is for Kialon's eyes alone.</Description>
  <LogDescription>Deliver Timothy's Letter to Kialon at Sylvanaar in the Blade's Edge Mountains.</LogDescription>
  <CompletionText>&lt;Kialon eyes you suspiciously.&gt;$B$BI don't know you, $R. Do you have business with me?</CompletionText>
  <RewardText>So you've brought Timothy's response?$B$B&lt;Kialon pauses a moment to read the letter, then laughs.&gt;$B$BHe's got everything under control, he says. Doesn't need help, he says. I could've predicted that!$B$BSome people never change. Look, he even took the time to correct my spelling.$B$B&lt;Kialon lets out a half-hearted sigh.&gt;$B$BI shouldn't have sent the letter. I forgot. The specialist always has the situation under control. Always.</RewardText>
  <Objectives />
</QuestData>