<?xml version="1.0" encoding="utf-8"?>
<QuestData xmlns:xsi="http://www.w3.org/2001/XMLSchema-instance" xmlns:xsd="http://www.w3.org/2001/XMLSchema" id="27208" type="Dungeon">
  <Title>The Dreadlord Balnazzar</Title>
  <Description>With the fall of the Scarlet Crusade, their disguised demon leader, Balnazzar, released the possessed body of Grand Crusader Dathrohan and went on a rampage, killing every remaining crusader here. He then used his necromantic power to raise them all as vile undead slaves.$B$BBalnazzar refers to his new army as the Risen. We cannot let him grow this army - they are extremely powerful and, unlike Arthas' Scourge, Balnazzar will not hold his forces back. Kill him while we still have a chance, $c.</Description>
  <PortraitGiverName>Balnazzar</PortraitGiverName>
  <PortraitGiverText>Lord of the Risen</PortraitGiverText>
  <LogDescription>Kill Balnazzar.</LogDescription>
  <RewardText>It's good we stopped Balnazzar now. Before long, his army would have overtaken all of Stratholme, giving him a powerful center for his new unholy empire.</RewardText>
  <Objectives />
</QuestData>