<?xml version="1.0" encoding="utf-8"?>
<QuestData xmlns:xsi="http://www.w3.org/2001/XMLSchema-instance" xmlns:xsd="http://www.w3.org/2001/XMLSchema" id="10143">
  <Title>Expedition Point</Title>
  <Description>Your battle prowess has been noted by high command, $c. They want to send you to the front lines to meet up with Rohamus's crew. They're radicals, devoted to the complete extermination of the Burning Legion, so you may fit right in...$B$BHead east about 400 paces, across the Valley of Bones, until you run into a destroyed fel reaver. You'll see Expedition Point where a Legion base used to stand. Once there, you are to report to Forward Commander Kingston.$B$BNow move out!</Description>
  <LogDescription>Report to Forward Commander Kingston at Expedition Point.</LogDescription>
  <QuestCompletionLog>Report to Forward Commander Kingston at Expedition Point in Hellfire Peninsula.</QuestCompletionLog>
  <RewardText>Glad to meet you, soldier.$B$BEnough chatting... now listen up -- I have a vital mission for you and I want you to succeed... and survive!</RewardText>
  <Objectives />
</QuestData>