{
    "Id": 77101,
    "Title": "Ingredient Quest Template",
    "Description": "Ricket sent word that she was here in Mechagon, so I came right away to help with the uh... research.\r\n\r\nI had the peons scour the island for any technology they could find. With da stuff we got here, we gonna make some amazing weapons to fight King Mechagon. Then afterwards, we get rich selling 'em!\r\n\r\nHelp me wrangle everyone's ideas into one perfect weapon!",
    "Objectives": [
        {
            "Hash": 888007968,
            "Text": "Speak with Ingredient Quest Giver"
        },
        {
            "Hash": 3137190458,
            "Text": "Do the Thing"
        }
    ]
}