<?xml version="1.0" encoding="utf-8"?>
<QuestData xmlns:xsi="http://www.w3.org/2001/XMLSchema-instance" xmlns:xsd="http://www.w3.org/2001/XMLSchema" id="37286" type="PvP">
  <Title>The Bloodshed Never Ends</Title>
  <Description>You are insatiable, gladiator! Let none doubt your voracious appetite for destruction and death!$B$BImperator Mar'gok will be very pleased to see you battling upon the arena floor of the Coliseum once more!$B$BAs before, I will accept nothing less than 100 lives!$B$BKill or be killed, gladiator!</Description>
  <LogDescription>Kill 100 Gladiators at the Coliseum in Highmaul.$B$BYou may access the Coliseum by talking to Kharg at Highmaul or Boneslag at your Gladiator's Sanctum.</LogDescription>
  <Objectives>
    <Objective id="276072">Gladiators Slain</Objective>
  </Objectives>
</QuestData>