{
    "Id": 78981,
    "Title": "Love is in the Air",
    "Description": "Smell these roses! My partner got them for me at the Gala of Gifts.\n\nInterested in seeing things yourself? Head to Durotar. There are gifts, and food, and you should taste the chocolate, it's delicious!",
    "ObjectivesText": "Visit the Gala of Gifts in Durotar, near Rocktusk Farm.",
    "ObjectivesCompletionText": "Speak with Mahaja Cloudsong at the Gala of Gifts.",
    "Objectives": [
        {
            "Hash": 3072402920,
            "Text": "[DNT] Arch glow"
        }
    ]
}