<?xml version="1.0" encoding="utf-8"?>
<QuestData xmlns:xsi="http://www.w3.org/2001/XMLSchema-instance" xmlns:xsd="http://www.w3.org/2001/XMLSchema" id="12457">
  <Title>The Chain Gun And You</Title>
  <Description>We've set up chain guns and barricades directly to the east and to the west. Our injured soldiers are hiding in both rooms - trying their best to not alert the mindless ghouls to their presence.$B$BNow that we have ammo, I need you to man one of the chain guns and use it to blast a path clear for our soldiers! Once you're on board, call a soldier out from hiding and then lay down heavy fire to keep the Scourge off him!$B$BGet a move on!</Description>
  <LogDescription>Ambo Cash at the Wintergarde Mausoleum in Dragonblight wants you to save 8 Injured 7th Legion Soldiers.</LogDescription>
  <CompletionText>Have you rescued our injured soldiers?</CompletionText>
  <RewardText>$n, I haven't seen heroics like that since Silithus!$B$BI'll be sure that each and every one of those soldiers puts in a recommendation to Lord Fordragon that you be promoted!$B$BNow, on to more pressing matters. We've gotten reports back from our scouts that Thel'zan is close.
</RewardText>
  <Objectives>
    <Objective id="262843">Injured 7th Legion Soldier Saved</Objective>
  </Objectives>
</QuestData>