{
    "Id": 66461,
    "Title": "The Field of Ferocity: Foe from the Volcano!",
    "Description": "One of the first volunteers for this competition hails from the Waking Shores. A big djaradin fellow, not quite as angry as his kin.\n \nHe just seems to enjoy the sport of fighting. Hey, that works for me.",
    "ObjectivesText": "Defeat Ceeqa the Peacetaker.",
    "RewardText": "What a show! I could feel sparks flying from here!",
    "Objectives": [
        {
            "Hash": 2138378218,
            "Text": "Ceeqa the Peacetaker slain"
        }
    ]
}