<?xml version="1.0" encoding="utf-8"?>
<QuestData xmlns:xsi="http://www.w3.org/2001/XMLSchema-instance" xmlns:xsd="http://www.w3.org/2001/XMLSchema" id="12637">
  <Title>Near Miss</Title>
  <Description>It was either wisdom or luck that prevented you from wearing this choker, $r.$b$bEither way, your acquiring it was no random occurance. You've been targeted by someone, or something....$b$bTake your choker to Bloodrose, here. Let her demonstrate the fate that nearly befell you.</Description>
  <LogDescription>Stefan at Ebon Watch wants you to take the Unliving Choker to Bloodrose Datura.</LogDescription>
  <CompletionText>Yes, $r?</CompletionText>
  <RewardText>Now you've observed the fate that was meant to befall you.$b$bAs I mentioned before, this was no coincidence. The creation of such a device is very involved, and the required resources would not be squandered on a random target.$b$bThe simple truth of the matter is this; You're wanted by the Scourge....</RewardText>
  <Objectives>
    <Objective id="263286">Choker's Purpose Exposed</Objective>
  </Objectives>
</QuestData>