<?xml version="1.0" encoding="utf-8"?>
<QuestData xmlns:xsi="http://www.w3.org/2001/XMLSchema-instance" xmlns:xsd="http://www.w3.org/2001/XMLSchema" id="38142">
  <Title>Archdruid of the Claw</Title>
  <Description>Near the southern edge of our forest you will find Sleeper's Barrow.$B$BThere, Archdruid Koda Steelclaw and her dedicated disciples carry out their sacred duty to observe the Emerald Dream.$b$bFind disciple Rylissa Bearsong in Steelclaw Vale and notify her of the crisis in the Grove of Cenarius.</Description>
  <LogDescription>Locate Steelclaw Vale.</LogDescription>
  <QuestCompletionLog>Speak to Rylissa Bearsong at Steelclaw Vale.</QuestCompletionLog>
  <RewardText>The forest already whispers of Malfurion's return. There are few among us who have not heard of his deeds.$B$BThe trees said he also travels with a companion, one named $n. Are you $Ghe:she;?</RewardText>
  <Objectives />
</QuestData>