<?xml version="1.0" encoding="utf-8"?>
<QuestData xmlns:xsi="http://www.w3.org/2001/XMLSchema-instance" xmlns:xsd="http://www.w3.org/2001/XMLSchema" id="2541">
  <Title>The Sleeping Druid</Title>
  <Description>The Gnarlpine shaman that inhabit this place have discovered a way of separating a sleeping druid's spirit from the physical body. The furbolg have animated my physical form and are using it to attack anyone that attempts to explore the Ban'ethil Barrow Den. I am now trapped in the Emerald Dream, powerless to stop this.$B$BYou must help me. The Gnarlpine shaman carry a strange charm which is used to perform this ritual, and I'd like to examine it. Please, $n, bring one to me.</Description>
  <LogDescription>Bring a Shaman Voodoo Charm to Oben Rageclaw in the Ban'ethil Barrow Den.</LogDescription>
  <CompletionText>If I can examine the charm, I may be able to figure out how to break the enchantment. Have you found one?</CompletionText>
  <RewardText>Thank you, $n.$B$BWhat an odd trinket this is... I can sense the vile aura emanating from it; this is a very powerful enchantment.</RewardText>
  <Objectives />
</QuestData>