<?xml version="1.0" encoding="utf-8"?>
<QuestData xmlns:xsi="http://www.w3.org/2001/XMLSchema-instance" xmlns:xsd="http://www.w3.org/2001/XMLSchema" id="60168">
  <Title>The Art of Taming</Title>
  <Description>I'm quite surprised to find this beast still alive and kicking. It appears to like you.

Before we finish, you had better learn how to wrangle multiple pets.

I'll give you one last lesson.</Description>
  <LogDescription>Learn how to dismiss, tame, and stable pets from Austin Huxworth.</LogDescription>
  <RewardText>Excellent work, $n. There's nothing left for me to teach you.

Gather as many wild beasts as you'd like. Just make sure not to lose focus on the ogres who are trying to kill us.</RewardText>
  <Objectives>
    <Objective id="397751">Use "Dismiss Pet" to temporarily dismiss your current pet</Objective>
    <Objective id="397752">Speak with Austin to summon and tame your new pet</Objective>
    <Objective id="397753">Speak with Austin to learn about pet stables</Objective>
  </Objectives>
</QuestData>