<?xml version="1.0" encoding="utf-8"?>
<QuestData xmlns:xsi="http://www.w3.org/2001/XMLSchema-instance" xmlns:xsd="http://www.w3.org/2001/XMLSchema" id="32654">
  <Title>Tear Down This Wall!</Title>
  <Description>The time has come. Our forces are well-enough entrenched here that we can risk pressing forward, into the Thunder King's lair. Unfortunately, it doesn't look like he'll be opening that gate anytime soon.$b$bI suppose we'll have to make a gate of our own then. Let me know when you're ready, $n.</Description>
  <LogDescription>Speak with Lady Jaina Proudmoore, then break into the lower city and secure it for the Alliance.</LogDescription>
  <RewardText>With your help, we're one giant step closer to our goal.</RewardText>
  <Objectives>
    <Objective id="270238">Speak to Lady Jaina Proudmoore to begin your mission</Objective>
    <Objective id="270239">Secure the lower city</Objective>
  </Objectives>
</QuestData>