{
    "Id": 76322,
    "Title": "The Face of Our Enemies",
    "Description": "Powerful foes lurk among the enemies Fyrakk summoned into the Emerald Dream.\n\nI have not seen Cassaphine since she came up out of the barrows. \n\nFind her, and assist our allies by striking down these leaders.",
    "ObjectivesText": "Defeat Fyrakk's powerful lieutenants and secure the battlefield.",
    "ObjectivesCompletionText": "Meet Merithra in the Fields of Reverie.",
    "Objectives": [
        {
            "Hash": 1188859888,
            "Text": "Cassaphine Scene Seen"
        },
        {
            "Hash": 2340798553,
            "Text": "Aronus Scene Seen"
        },
        {
            "Hash": 3263414195,
            "Text": "Apostle Fenarelle slain"
        },
        {
            "Hash": 3910243012,
            "Text": "Stormbrand Ko'mal slain"
        }
    ]
}