<?xml version="1.0" encoding="utf-8"?>
<QuestData xmlns:xsi="http://www.w3.org/2001/XMLSchema-instance" xmlns:xsd="http://www.w3.org/2001/XMLSchema" id="28330" type="Group">
  <Title>Trail of Filth</Title>
  <Description>The trail of filth and anger leads into the ruined town hall. Surely there is a slime breeding pool inside the structure. Fight your way inside and deal with whatever angry slime-breeder that you encounter!$B$BShould you succeed Serge Hinott at the Ruins of Southshore will surely want to hear about it.</Description>
  <PortraitGiverName>Chet</PortraitGiverName>
  <PortraitGiverText>You're stewed, buttwad!</PortraitGiverText>
  <LogDescription>Kill Chet the Slime-Breeder.</LogDescription>
  <CompletionText>Yes?</CompletionText>
  <RewardText>Perhaps with Chet vanquished, the lethality levels of this place will decrease a tad faster. A job well done, $n!</RewardText>
  <Objectives />
</QuestData>