{
    "Id": 31941,
    "Title": "Squash Those Foul Odors",
    "Description": "Grandpa always said, \"A squash a week, and your tail won't reek.\"\n\n<Yoon subtly sniffs the air.>\n\nYup. I think it's been about a week. Could you help me plant a Jade Squash?",
    "ObjectivesText": "Plant a Jade Squash in Sunsong Ranch. You can purchase seeds from Merchant Greenfield in the Halfhill Market.",
    "AreaDescription": null,
    "PortraitGiverName": null,
    "PortraitGiverText": null,
    "PortraitTurnInName": null,
    "PortraitTurnInText": null,
    "ObjectivesCompletionText": null,
    "CompletionText": null,
    "RewardText": null,
    "Objectives": [
        {
            "Hash": 174355845,
            "Text": "Plant Jade Squash Seeds"
        }
    ]
}