{
    "Id": 32045,
    "Title": "Children of the Water",
    "Description": "We are all children of the water here in the Valley of the Four Winds. It nourishes us, it grows our vegetables, it brings us life.\n\nSome creatures, however, drink too deeply from the water. They grow too large, and must be eliminated before they cause havoc to those around them.\n\nI am but a simple stonecarver. You, on the other hand...",
    "ObjectivesText": "Slay Kracor, Thundergill, and Succula.",
    "AreaDescription": null,
    "PortraitGiverName": null,
    "PortraitGiverText": null,
    "PortraitTurnInName": null,
    "PortraitTurnInText": null,
    "ObjectivesCompletionText": null,
    "CompletionText": null,
    "RewardText": "Let this be a lesson to you: don't drink too much of the water.\n\nWhy do you think we have such a big brewery?",
    "Objectives": [
        {
            "Hash": 2572783699,
            "Text": "Kracor slain"
        },
        {
            "Hash": 1791586251,
            "Text": "Succula slain"
        }
    ]
}