{
    "Id": 77305,
    "Title": "Поза пісками",
    "Description": "<Втрачені в часі фрагменти тепер з'єднані, щоб сформувати кам'яну табличку, але багато написів на ній зношені та неповні.\n\nЗахисниця Катос захоче це побачити.>",
    "ObjectivesText": "Поверніть неповну табличку захисниці Катос.",
    "AreaDescription": null,
    "PortraitGiverName": null,
    "PortraitGiverText": null,
    "PortraitTurnInName": null,
    "PortraitTurnInText": null,
    "ObjectivesCompletionText": null,
    "CompletionText": null,
    "RewardText": null,
    "Objectives": [
        {
            "Hash": 922751225,
            "Text": "Неповна табличка"
        }
    ]
}