{
    "Id": 82678,
    "Title": "Архіви: Перший диск",
    "Description": "Я рада повідомити про успіхи у відновленні титанічного Сховища пам'яті в Архіві. Центральний термінал вже працює, але частина його внутрішнього механізму з часом вийшла з ладу.\n\nДістати запчастини для нього буде непросто, тому нам потрібна твоя допомога. Ходімо зі мною до Сховища пам'яті. Ми можемо обговорити з Даґраном, що саме нам потрібно.",
    "ObjectivesText": "Зустріньтеся з Даґраном у Сховищі пам'яті та допоможіть йому знайти фрагменти титанічного диска.\n\nЧастинки титанічного диска можна здобути з небезпечних створінь та скарбів по всьому Каз-Алґару.",
    "ObjectivesCompletionText": "Поверніться до Даґрана у Сховище пам'яті.",
    "Objectives": [
        {
            "Hash": 3392013246,
            "Text": "Продовжуйте вашу кампанію, щоб розблокувати Архіви"
        },
        {
            "Hash": 3675445660,
            "Text": "Зустріньтеся з Брінтою у Сховищі пам'яті"
        },
        {
            "Hash": 4090012181,
            "Text": "Поговоріть з Брінтою"
        },
        {
            "Hash": 2098074425,
            "Text": "Фрагмент титанічного диска"
        }
    ]
}