{
    "Id": 72261,
    "Title": "More Than a Prison?",
    "Description": "<The ancient artifact appears elemental in nature. Lillian Brightmoon in Valdrakken might be able to tell more.>",
    "ObjectivesText": "Bring the Ancient Vault Artifact to Lillian Brightmoon.",
    "RewardText": "The Incarnates were locked away in the Vault, but aside from that we know very little either about it or its prisoners.\n\nArtifacts like this can shed light on their culture, their history, and... their power. Studying them could improve our odds in defeating the primalists. Bring me more of these I will reward you with supplies.\n\nOh, and I will pen a note to Caretaker Jakes reminding her of your continued assistance of the Dragonscale Expedition.",
    "Objectives": [
        {
            "Hash": 3145075746,
            "Text": "Ancient Vault Artifact"
        }
    ]
}