<?xml version="1.0" encoding="utf-8"?>
<QuestData xmlns:xsi="http://www.w3.org/2001/XMLSchema-instance" xmlns:xsd="http://www.w3.org/2001/XMLSchema" id="33786">
  <Title>Crippled Caravan</Title>
  <Description>I'm getting reports that the botani have started leaving their bloom and attacking wandering travelers. This is most unusual.$b$bWe already dispatched a number of rangari to try and resolve this issue.$b$bA caravan from Azeroth passed through here recently, you should probably check on your people to ensure their safety.</Description>
  <LogDescription>Find Fiona's Caravan in Shadowmoon Valley.</LogDescription>
  <RewardText>Commander! Am I glad to see you.$b$bWe have a situation here.</RewardText>
  <Objectives>
    <Objective id="271981">Fiona found</Objective>
  </Objectives>
</QuestData>