{
    "Id": 73002,
    "Title": "Temporal Immunity",
    "Description": "Zhusadormu has been trying hard to keep his powers in check.\n\nWhile we may not be able to prevent his allergies, he does not have to jump through time with each sneeze.\n\nWurallie believes she can test his control. Please go to the Waking Shores and help them with this lesson.",
    "ObjectivesText": "Help Zhusadormu confront his allergies during a pet battle.",
    "RewardText": "A sneeze without a teleport! A breakthrough to be proud of.\n\nNow that he won't get lost, Zhusadormu will want to join you on some quests",
    "Objectives": [
        {
            "Hash": 1198846075,
            "Text": "Visit Wurallie in the Waking Shores"
        },
        {
            "Hash": 3653545382,
            "Text": "[DNT]Tracker: Started Battle With Wuralie Once"
        },
        {
            "Hash": 1615381882,
            "Text": "Defeat Wurallie in a Pet Battle with Annuna on your team"
        },
        {
            "Hash": 2132514319,
            "Text": "[DNT]Tracker: Beat Wurallie At All"
        }
    ]
}