<?xml version="1.0" encoding="utf-8"?>
<QuestData xmlns:xsi="http://www.w3.org/2001/XMLSchema-instance" xmlns:xsd="http://www.w3.org/2001/XMLSchema" id="27261">
  <Title>Questioning Reethe</Title>
  <Description>It took a long time, but I found Reethe. He hide good for a human.$b$bOgron worried that he might be crazy after so much time in swamp. You come with me for we go get answers from him.</Description>
  <AreaDescription>Question Reethe with Ogron</AreaDescription>
  <LogDescription>Go with Ogron to speak with Reethe.</LogDescription>
  <QuestCompletionLog>Return to Krog at Brackenwall Village in Dustwallow Marsh.</QuestCompletionLog>
  <RewardText>Hmph. It is good that Reethe will no longer be lurking around the swamp, but it is a shame that humans are built so frail that he could not recover from a little arrow wound.$b$bIt seems that this thread of the mystery has led nowhere, and we must look elsewhere.</RewardText>
  <Objectives />
</QuestData>