<?xml version="1.0" encoding="utf-8"?>
<QuestData xmlns:xsi="http://www.w3.org/2001/XMLSchema-instance" xmlns:xsd="http://www.w3.org/2001/XMLSchema" id="26495">
  <Title>Chabal</Title>
  <Description>Chabal, that troll over by the botanical gardens/biological weapons lab, is a special guest.  He's a representative of the Zandalari trolls, and has traveled quite far to stay with us.$b$b&lt;Sassy places some of the items you've collected in a small parcel and hands it to you.&gt;$b$bHere, give this to him.  Tell him that the Zandalari are always welcome at Hardwrench Hideaway!  And mention that referrals are key to maintaining our business!</Description>
  <LogDescription>Bring Sassy's Largesse to Chabal in Hardwrench Hideaway.</LogDescription>
  <CompletionText>Care to explain yourself, $c?</CompletionText>
  <RewardText>&lt;The troll looks into the package.&gt;$b$bYou have my thanks.$b$bI have been waiting for you to approach me, $r.  I have identified you as the most promising $r here in this strange town.  I have a task for you, if you would be willing to take it.</RewardText>
  <Objectives />
</QuestData>