<?xml version="1.0" encoding="utf-8"?>
<QuestData xmlns:xsi="http://www.w3.org/2001/XMLSchema-instance" xmlns:xsd="http://www.w3.org/2001/XMLSchema" id="26753">
  <Title>The Halls of the Dead</Title>
  <Description>&lt;In front of you, the bare earth slopes down towards the dark entrance to the crypts.&gt;$B$B&lt;You can feel the tug of the lightforged artifact urging you towards it. Perhaps the other piece is down there?&gt;</Description>
  <LogDescription>Find the Lightforged Arch within the Dawning Woods Catacombs.</LogDescription>
  <RewardText>&lt;In the dirt of this alcove, your eye catches the shine of brilliant metal. You've found another piece of the artifact!&gt;</RewardText>
  <Objectives />
</QuestData>