<?xml version="1.0" encoding="utf-8"?>
<QuestData xmlns:xsi="http://www.w3.org/2001/XMLSchema-instance" xmlns:xsd="http://www.w3.org/2001/XMLSchema" id="34072">
  <Title>Tar Get of Opportunity</Title>
  <Description>General Vul'gath leads this band of Thunderlord. He is a coward and hides in his hut, yelling orders at his warriors through the walls.$b$bWe will need to show him that his flimsy defenses can not stand against the Frostwolves!$b$bI'll need some tar to carry this out. There are a couple of tar pits to the south, go gather a few globs from the oozes that reside there and bring them to me.</Description>
  <LogDescription>Gather 5 Globs of Sticky Tar from the Black Tar's in the Bones of Agurak.</LogDescription>
  <RewardText>Ugh, those smell awful! No, I don't need to see them. I'll take you at your word that you have them all.$b$bLet's get a move on before another Thunderlord patrol stumbles upon me.</RewardText>
  <Objectives />
</QuestData>