<?xml version="1.0" encoding="utf-8"?>
<QuestData xmlns:xsi="http://www.w3.org/2001/XMLSchema-instance" xmlns:xsd="http://www.w3.org/2001/XMLSchema" id="25204">
  <Title>Release the Valves</Title>
  <Description>We have to stop Trade Prince Gallywix's oil supply and bring his machines to a grinding halt.$B$BWe're going to need you to go out to the KTC Oil Platform and release the valves to overload the coolant system. After you do that, head to the platform control panel on the platform and set it to blow.</Description>
  <LogDescription>Release Valves #1 - 4.</LogDescription>
  <RewardText>All of the lights and indicators on the control panel are going crazy!</RewardText>
  <Objectives>
    <Objective id="256938">Valve #1 released</Objective>
    <Objective id="256939">Valve #2 released</Objective>
    <Objective id="256940">Valve #3 released</Objective>
    <Objective id="256941">Valve #4 released</Objective>
  </Objectives>
</QuestData>