<?xml version="1.0" encoding="utf-8"?>
<QuestData xmlns:xsi="http://www.w3.org/2001/XMLSchema-instance" xmlns:xsd="http://www.w3.org/2001/XMLSchema" id="12109">
  <Title>Report to Gryan Stoutmantle... Again</Title>
  <Description>The Westfall boys were sent east to look for a path into the northern territories.  Their secondary objective is to secure strategic resource points, so I'm sure they wouldn't mind investigating a mine.$B$BLook for the Westfall Brigade encampment far to the northeast and seek out Gryan Stoutmantle.  You might remember him if you ever spent any time in Westfall.  Make sure to tell him I sent you.$B$BHe'll be more than happy to let you claim a functioning mine for the king.</Description>
  <LogDescription>Speak to Captain Gryan Stoutmantle at the Westfall Brigade Encampment.</LogDescription>
  <RewardText>Dumont sent you?  Very well.  Let's see what you can do for us.</RewardText>
  <Objectives />
</QuestData>