<?xml version="1.0" encoding="utf-8"?>
<QuestData xmlns:xsi="http://www.w3.org/2001/XMLSchema-instance" xmlns:xsd="http://www.w3.org/2001/XMLSchema" id="30932">
  <Title>Father's Footsteps</Title>
  <Description>Yes, the boy's father - Sentinel Ku-Yao - has gone missing. He could be any number of places... we have no shortage of enemies these days.$b$bYou're free to look around, if you wish. You might start by looking for his yak, or by asking Sentinel Yalo what he knows.</Description>
  <LogDescription>Find Father's Bedroll, Father's Shield, Ha-Cha, and Sentinel Yalo.</LogDescription>
  <CompletionText>Any luck?</CompletionText>
  <RewardText>No shield, no crossbow, no yak... something bad has happened to dad.</RewardText>
  <Objectives>
    <Objective id="267874">Find Father's Bedroll</Objective>
    <Objective id="267875">Find Father's Shield</Objective>
    <Objective id="267876">Find Ha-Cha</Objective>
    <Objective id="267877">Find Sentinel Yalo</Objective>
  </Objectives>
</QuestData>