<?xml version="1.0" encoding="utf-8"?>
<QuestData xmlns:xsi="http://www.w3.org/2001/XMLSchema-instance" xmlns:xsd="http://www.w3.org/2001/XMLSchema" id="66831">
  <Title>Home Is Where the Frogs Are</Title>
  <Description>All the frogs are rounded up, $n! I guess we're, uh, taking the frogs to Akora anyway. They'll be safe at the Life Pools until the hornswogs get bored and move on.

Um, well, I guess we didn't find anything to cheer up Akora. I hope she understands...</Description>
  <LogDescription>Meet Keshki back at the Life Pools to release the rescued frogs.</LogDescription>
  <Objectives>
    <Objective id="428521">Frog Box Opened</Objective>
    <Objective id="428527">Frogs Released</Objective>
  </Objectives>
</QuestData>