<?xml version="1.0" encoding="utf-8"?>
<QuestData xmlns:xsi="http://www.w3.org/2001/XMLSchema-instance" xmlns:xsd="http://www.w3.org/2001/XMLSchema" id="61871">
  <Title>To Current Matters</Title>
  <Description>Ye've done good here, champion. MOTHER and I will be figurin' out what te do next.

Ye best get back te matters at hand, and do what ye can te empower that necklace o' yours.

I've got ways te reach ye once MOTHER and I have fixed things up here.</Description>
  <PortraitGiverName>Magni Bronzebeard</PortraitGiverName>
  <PortraitGiverText>Azeroth is in danger, you're needed in Silithus!</PortraitGiverText>
  <LogDescription>Return to Nathanos Blightcaller on the Banshee's Wail in Zuldazar.</LogDescription>
  <QuestCompletionLog>Return to Nathanos Blightcaller on the Banshee's Wail in Zuldazar.</QuestCompletionLog>
  <Objectives />
</QuestData>