<?xml version="1.0" encoding="utf-8"?>
<QuestData xmlns:xsi="http://www.w3.org/2001/XMLSchema-instance" xmlns:xsd="http://www.w3.org/2001/XMLSchema" id="57649">
  <Title>Whisper of Hope</Title>
  <Description>Akarek's demise has cast a dark shadow upon our house... but it is in the shadows where we thrive.

I know that not all the Eyes have perished. They could lie in wait, hidden for eternity, if such was demanded of them.

But it is time to reclaim our destiny. Take my sigil through the wreckage and awaken any Eyes who remain.

We will seize our victory.</Description>
  <LogDescription>Use Vashj's Sigil to rally survivors of the House of Eyes.</LogDescription>
  <QuestCompletionLog>Speak with Whisperer Vyn beneath Nurakkir.</QuestCompletionLog>
  <RewardText>The baroness inspires great dedication. I trust in her plans.</RewardText>
  <Objectives>
    <Objective id="392848">Rally survivors with Mark of Vashj</Objective>
  </Objectives>
</QuestData>