<?xml version="1.0" encoding="utf-8"?>
<QuestData xmlns:xsi="http://www.w3.org/2001/XMLSchema-instance" xmlns:xsd="http://www.w3.org/2001/XMLSchema" id="66033">
  <Title>To the... Past?</Title>
  <Description>It is regrettable that we could not stabilize Chronormu, but there is another potential location where we may be able to catch her and bring an end to her fall through time. 

&lt;Nozdormu frowns.&gt;

The glimpses of this timeline past are... strange. Even among some of the visions I have witnessed in my life.

Be on your guard, $n. I am uncertain what you will face, but it is powerful and... oddly familiar.</Description>
  <LogDescription>Take the portal and meet with Andantenormu in Azmerloth.</LogDescription>
  <QuestCompletionLog>Take the portal and meet with Andantenormu in Azmerloth.</QuestCompletionLog>
  <RewardText>Whatever I expected... This is not it.</RewardText>
  <Objectives>
    <Objective id="432124">Portal to Azmerloth taken</Objective>
  </Objectives>
</QuestData>