<?xml version="1.0" encoding="utf-8"?>
<QuestData xmlns:xsi="http://www.w3.org/2001/XMLSchema-instance" xmlns:xsd="http://www.w3.org/2001/XMLSchema" id="63584">
  <Title>A Triumphant Return</Title>
  <Description>This temple represents a new dawn for Bastion, $n.

The Temple of Devotion will stand as a place of fellowship. We will work with the Forsworn, as well as aspirants and kyrian of all experience and backgrounds, to forge a future of which all can be proud.

Let us return to Elysian Hold. I request that you join us for a momentous occasion--the ascension of a new Paragon and the creation of a new sigil.</Description>
  <LogDescription>Meet Kalisthene at Elysian Hold. 

The Kyrian Courier can provide a flight.</LogDescription>
  <QuestCompletionLog>Meet Kalisthene at Elysian Hold.</QuestCompletionLog>
  <Objectives>
    <Objective id="421232">Speak to Kyrian Courier to fly to Elysian Hold</Objective>
  </Objectives>
</QuestData>