<?xml version="1.0" encoding="utf-8"?>
<QuestData xmlns:xsi="http://www.w3.org/2001/XMLSchema-instance" xmlns:xsd="http://www.w3.org/2001/XMLSchema" id="63680">
  <Title>Out On the Edge</Title>
  <Description>It sounds like Huln was taken elsewhere, and by the Stonewright herself!

We should look for signs she came through the area. Hopefully that will lead us to Huln!</Description>
  <LogDescription>Track down Huln Highmountain.</LogDescription>
  <Objectives>
    <Objective id="420043">Speak with Terrified Stoneborn</Objective>
    <Objective id="420135">Huln Found</Objective>
    <Objective id="420136">Huln Rescued</Objective>
    <Objective id="420137">Speak with the Stonewright</Objective>
  </Objectives>
</QuestData>