<?xml version="1.0" encoding="utf-8"?>
<QuestData xmlns:xsi="http://www.w3.org/2001/XMLSchema-instance" xmlns:xsd="http://www.w3.org/2001/XMLSchema" id="64555">
  <Title>Surveying Secrets</Title>
  <Description>Each of the covenants have provided their own specialists in their areas of expertise. A few of them have taken to the field to scout this unknown land.

Speak with them. They should all be keeping a report of their survey. Return them to me.</Description>
  <LogDescription>Speak with the forward scouts in Korthia.</LogDescription>
  <RewardText>Most of this information is useful. My thanks, Maw Walker.</RewardText>
  <Objectives>
    <Objective id="421111">Maldraxxi scout spoken with</Objective>
  </Objectives>
</QuestData>