{
    "Id": 56034,
    "Type": null,
    "Category": null,
    "Title": "Re-sizing the Situation",
    "Description": "The Re-Sizer v9.0.1 barely works on inanimate objects. I have no idea what it will do to organic matter!\n\nBut if we do nothing, Henry will die!\n\nDesperate times call for massively experimental science, $n.\n\nTake the Re-Sizer v9.0.1. I'll follow you around and calibrate it.\n\nWe're going to whip up a giant boar!",
    "ObjectivesText": "Use the Re-Sizer v9.0.1 on $1oa Wandering Boars.",
    "AreaDescription": "",
    "PortraitGiverName": "",
    "PortraitGiverText": "",
    "PortraitTurnInName": "",
    "PortraitTurnInText": "",
    "ObjectivesCompletionText": "Speak with Captain Garrick.",
    "CompletionText": null,
    "RewardText": "I never thought I'd be so relieved to be face to face with a giant, scientifically enhanced boar.\n\nLet's go save my son.",
    "Objectives": [
        {
            "Hash": 2953138165,
            "Text": "Re-Sizer v9.0.1 tested on Wandering Boars"
        }
    ]
}