<?xml version="1.0" encoding="utf-8"?>
<QuestData xmlns:xsi="http://www.w3.org/2001/XMLSchema-instance" xmlns:xsd="http://www.w3.org/2001/XMLSchema" id="31512">
  <Title>A Witness to History</Title>
  <Description>The celestials are allowing us back into the Vale! This will be a sight to behold.$b$bWe shouldn't waste any time. Head to the Gate of the August Celestials at the southern edge of Kun-Lai Summit and speak with me there.</Description>
  <LogDescription>Speak with Anduin Wrynn at the Gate of the August Celestials.</LogDescription>
  <RewardText>Welcome to the Shrine of Seven Stars.$B$BI wish I could bring you better tidings, $c, but the situation here in the Vale is quite dire.$B$BThere is much to do, but first, rest and explore the city.$B$BWelcome to the Vale.</RewardText>
  <Objectives>
    <Objective id="268655">Speak to Anduin at the Gate of the August Celestials</Objective>
  </Objectives>
</QuestData>