<?xml version="1.0" encoding="utf-8"?>
<QuestData xmlns:xsi="http://www.w3.org/2001/XMLSchema-instance" xmlns:xsd="http://www.w3.org/2001/XMLSchema" id="9567">
  <Title>Know Thine Enemy</Title>
  <Description>It's good to see another new face here in Blood Watch, $c. Although the blood elves are the most immediate threat, there are other sinister creatures that call Bloodmyst Isle home.$B$BThe Nazzivus satyr are of particular concern. They are foul, demonic creatures, commanding dark magics and feeding on the corruption created by the Exodar's crash.$B$BWe must hold them in check, but first we must learn more about them. Go southwest to Nazzivian and learn what you can from their grotesque monument.</Description>
  <LogDescription>Find the Nazzivus Monument in Nazzivian and retrieve a Nazzivus Monument Glyph. Return to Vindicator Aalesia in Blood Watch when you have one of the glyphs.</LogDescription>
  <CompletionText>Were you successful in obtaining knowledge of the Nazzivus satyr?</CompletionText>
  <RewardText>Well done, $n. Let me see what I can learn from this glyph, so we can plan our next move.</RewardText>
  <Objectives />
</QuestData>