{
    "Id": 78631,
    "Title": "Розмова з Мовцями",
    "Description": "Я чула про проблему неподалік і, здається, знаю, що не так.\n\nКолись у нас була шахта на північному сході від Ґундарґаза. Коли ми виїхали звідти, там поселились кобольди.\n\nДавно ми не чули про цих кобольдів, але схоже, що тепер вони на нас нападають! І Верховний Мовець нічого з цим не робить.\n\nХтось має щось зробити. Якщо ми зможемо з цим розібратись, більше Механомовців послухають нас. Якщо Верховний Мовець нічого не зробить, ми зробимо.",
    "ObjectivesText": "Заспокойте захисників Ґундарґаза на шляху до Загублених копалень.",
    "RewardText": "Приємно бачити, що деякі з кобольдів не дуже зацікавлені цією війною.",
    "Objectives": [
        {
            "Hash": 3242830905,
            "Text": "Захисники заспокоєні"
        },
        {
            "Hash": 606791268,
            "Text": "Точка огляду розвідана"
        }
    ]
}