{
    "Id": 80434,
    "Title": "У Глибини",
    "Description": "Отже, вперед і вниз. Краще підемо за Мовицею Брінтою і подивимось, в якому стані неруби залишили її дім.\n\nКоли прийде час, Маґні, Даґран і я супроводимо тебе вниз. Ти не {sex|міг би|могла б} прогулятися вперед і переконатися, що нас там чекає теплий прийом?",
    "ObjectivesText": "Знайдіть Мовицю Брінту в кінці Шляху до Ядра.",
    "RewardText": "В ім'я Титанів! Здається, неруби пошкодили нашу станцію... проте, я не бачу тут самих павукоподібних дідьків. Лише нещасних Механомовців...",
    "Objectives": []
}