{
    "Id": 30956,
    "Title": "The Siege Swells",
    "Description": "Today's mantid swarm is among the worst I've seen. We are lucky to have Niuzao join us in battle.\n\nHelp him, $c. Return to the courtyard, and join in the defense of our temple.",
    "ObjectivesText": "Defeat 25 Sra'thik attackers at Niuzao Temple.",
    "AreaDescription": null,
    "PortraitGiverName": null,
    "PortraitGiverText": null,
    "PortraitTurnInName": null,
    "PortraitTurnInText": null,
    "ObjectivesCompletionText": null,
    "CompletionText": null,
    "RewardText": null,
    "Objectives": [
        {
            "Hash": 3281413100,
            "Text": "Sra'thik attacker slain"
        }
    ]
}