<?xml version="1.0" encoding="utf-8"?>
<QuestData xmlns:xsi="http://www.w3.org/2001/XMLSchema-instance" xmlns:xsd="http://www.w3.org/2001/XMLSchema" id="25412">
  <Title>The Name Never Spoken</Title>
  <Description>We called upon the fury and flame of the One, my former master.$B$BThe Inferno is by His design.$B$BHis true name is never uttered, it holds His power.$B$BEach of us was told but a piece. Each piece engraved on a firestone.$B$BThe One's true name is here, in the Inferno. Seek the three stones...</Description>
  <LogDescription>Assemble the true name by examining the three Firestones.</LogDescription>
  <RewardText>Yes, yes! Show me the runes you discovered.$B$B"Vol'talo Thol'embaar." That's the name of your real enemy.$B$BPresumably you're dealing with one of Ragnaros's generals, sent here to scorch the mountainside and pave the way for his conquest.$B$BI will show you how to crush him.</RewardText>
  <Objectives>
    <Objective id="251639">Northern Firestone Examined</Objective>
    <Objective id="251640">Central Firestone Examined</Objective>
    <Objective id="251641">Southern Firestone Examined</Objective>
  </Objectives>
</QuestData>