{
    "Id": 56034,
    "Title": "Зміна масштабу ситуації",
    "Description": "Розмірозмінювач v9.0.1 майже не працює на неживих об'єктах. Тому я навіть гадки не маю, що він зробить з живою матерією!\n\nАле якщо ми нічого не зробимо, Генрі помре!\n\nВідчайдушні часи вимагають масштабних наукових експериментів, $n.\n\nВізьми Розмірозмінювач v9.0.1. Я піду за тобою і відкалібрую його.\n\nМи завалимо велетенського кабана!",
    "ObjectivesText": "Застосуйте Розмірозмінювач v9.0.1 на 3 Блукаючих кабанах.",
    "ObjectivesCompletionText": "Поговоріть з Капітаном Ґеррік.",
    "RewardText": "Я ніколи не думав, що відчую таке полегшення, опинившись віч-на-віч з велетенським, науково вдосконаленим кабаном.\n\nХодімо врятуємо мого сина.",
    "Objectives": [
        {
            "Hash": 2953138165,
            "Text": "Розмірозмінювач v9.0.1 протестовано на Блукаючих кабанах"
        }
    ]
}