{
    "Id": 66006,
    "Title": "Повернення до Роші",
    "Description": "Баба відпочив, а припаси Роші ми відібрали. Ми можемо повернутися, не дратуючи її більше.\n\nВізьми декілька коробок, коли будеш виходити. Я надішлю воїнів за рештою.",
    "ObjectivesText": "Поверніть припаси Роші.",
    "RewardText": "У тебе є припаси? Добре.\n\nЗалиш їх біля кузні.\n\n<Роша озирається і хмуриться.>",
    "Objectives": [
        {
            "Hash": 3485120559,
            "Text": "Припаси"
        }
    ]
}