{
    "Id": 82682,
    "Title": "Льо-електрік смаколік",
    "Description": "Хмарогрифи не можуть кружляти вічно, і я не можу допустити, щоб ще більше з них загинуло. Але, можливо, вони б осіли, якби ми спокусили їх улюбленою їжею?\n\nВугрі, що плавають у цих водах, несуть невеликий електричний заряд, схожий на той, що є в мохошерстів, улюблених їхніми швидшими та сильнішими родичами — грозовими хмарогрифами. Якось я припустив, що хмарогрифи можуть полюбити вугрів з тих самих причин.\n\nІ зізнаюся... я годую їх вугрями відтоді.\n\nЗбери їх трохи й спробуй.",
    "ObjectivesText": "Зберіть 10 електричних вугрів.",
    "CompletionText": "Вугрі, можливо, не такі наелектризовані, як мохошерсти Гуляйкраю, але хмарогрифи, здається, саме за це і надають їм перевагу.",
    "RewardText": "Це має підійти.\n\nСподіваюся, тебе не сильно вдарило струмом, поки ти їх збирав.\n\nМи можемо відновити трохи енергії хмарогрифам і показати їм, що приземлятися безпечно.",
    "Objectives": [
        {
            "Hash": 4202161812,
            "Text": "Електричний вугор"
        },
        {
            "Hash": 2081128519,
            "Text": ""
        },
        {
            "Hash": 2085060683,
            "Text": ""
        },
        {
            "Hash": 2088992847,
            "Text": ""
        },
        {
            "Hash": 2092925011,
            "Text": ""
        },
        {
            "Hash": 2096857175,
            "Text": ""
        },
        {
            "Hash": 2100789339,
            "Text": ""
        },
        {
            "Hash": 2104721503,
            "Text": ""
        }
    ]
}