{
    "Id": 76385,
    "Title": "Небезпечне садівництво",
    "Description": "Хоч нас і перевершують чисельністю військ, але ця територія підвладна мені. І я маю спосіб зрівняти наші шанси.\n\nВізьми цей мішечок з насінням. Посади його по всьому каньйону дикого вогню, і чарівні дракончики Сну перетворять саджанців на дереванів.\n\nЯкщо пощастить, вони відвернуть увагу від нашого фронту та зміцнять наші сухопутні війська.",
    "ObjectivesText": "Посадіть 6 насінин Сну в Каньйоні дикого вогню.",
    "AreaDescription": null,
    "PortraitGiverName": null,
    "PortraitGiverText": null,
    "PortraitTurnInName": null,
    "PortraitTurnInText": null,
    "ObjectivesCompletionText": null,
    "CompletionText": null,
    "RewardText": null,
    "Objectives": [
        {
            "Hash": 2188816871,
            "Text": "Насіння Сну посаджено"
        },
        {
            "Hash": 4096380540,
            "Text": "Convo 1"
        },
        {
            "Hash": 4113156733,
            "Text": "Convo 2"
        },
        {
            "Hash": 4129932926,
            "Text": "Convo 3"
        },
        {
            "Hash": 4146709119,
            "Text": "Convo 4"
        },
        {
            "Hash": 4163485312,
            "Text": "Convo 5"
        }
    ]
}