{
    "Id": 76464,
    "Title": "Торігніри",
    "Description": "Торігніри зі Штормхейму мають силу й міць, щоб значно допомогти нам у захисті Амірдрассіла, але вони ще не прибули на Драконячі острови. Я підозрюю, що... Одін завадив їхній подорожі.\n\nМи підемо і поговоримо з їхнім Матріархом. Гнівіон каже мені, що її потомство податливе до вашого роду та допомоги іншим. \n\nМи проведемо розслідування.",
    "ObjectivesText": "Speak with the Thorignir Broodmother.",
    "AreaDescription": null,
    "PortraitGiverName": null,
    "PortraitGiverText": null,
    "PortraitTurnInName": null,
    "PortraitTurnInText": null,
    "ObjectivesCompletionText": null,
    "CompletionText": null,
    "RewardText": null,
    "Objectives": [
        {
            "Hash": 3665444469,
            "Text": "Скористайтесь порталом у \"Смаженому барані\""
        },
        {
            "Hash": 1802286625,
            "Text": "Поговоріть з Тримджаріс"
        },
        {
            "Hash": 2297111049,
            "Text": "Поговоріть з Віранот"
        }
    ]
}