{
    "Id": 66184,
    "Title": "Якорі життя",
    "Description": "Ґрунтуючись на моїх дослідженнях, я вважаю, що є спосіб відновити зв’язки Ізери зі Смарагдовим Сном, щоб ми могли наблизити її до Азероту.\n\nКоли Ізера померла, Зимова Королева використала власну силу, щоб відновити її в Арденвельді. Наразі вона там прив’язана, але я думаю, якщо ми зможемо просто переправити Ізеру в Смарагдовий Сон, ми зможемо використати ці якорі, щоб утримати її там.\n\nАле я забігаю наперед.\n\nПо-перше, ми маємо наповнити ці якоря силою цих Смарагдових сліз.",
    "ObjectivesText": "Наповніть Інертні якорі Смарагдовими сльозами.",
    "AreaDescription": null,
    "PortraitGiverName": null,
    "PortraitGiverText": null,
    "PortraitTurnInName": null,
    "PortraitTurnInText": null,
    "ObjectivesCompletionText": null,
    "CompletionText": null,
    "RewardText": null,
    "Objectives": [
        {
            "Hash": 990334374,
            "Text": "Наповніть перший якір"
        },
        {
            "Hash": 2127910286,
            "Text": "Наповніть другий якір"
        },
        {
            "Hash": 1884895545,
            "Text": "Наповніть третій якір"
        },
        {
            "Hash": 1381219991,
            "Text": "Зачекайте на прибуття Мерітри"
        }
    ]
}