{
    "Id": 72602,
    "Title": "Optimistic Mystic",
    "Description": "I'm sure I can find this Bovan Windtotem--but I will need a few items from you.\n\nFirst, I need a selection of flowers that grow at the base of the springs. They have the specific properties we are looking for.\n\nNext, I require the heart of a salamanther. A stronger heart will better our chances--look for the strongest you can find!\n\nI can gather the rest of the materials on my own.",
    "ObjectivesText": "Collect a Strong Salamanther Heart and 8 Geyser Flowers.",
    "AreaDescription": null,
    "PortraitGiverName": null,
    "PortraitGiverText": null,
    "PortraitTurnInName": null,
    "PortraitTurnInText": null,
    "ObjectivesCompletionText": "Meet Boku just north of the Ohn'iri Springs.",
    "CompletionText": null,
    "RewardText": null,
    "Objectives": [
        {
            "Hash": 2015003459,
            "Text": "Geyser Flower"
        }
    ]
}