{
    "Id": 65780,
    "Title": "Proving Oneself",
    "Description": "A gift from dragons may impress some centaur, but Clan Shikaar must see how well you hunt.\n\nOne of our hunting parties just brought down a proto-dragon infused with the power of flame. Prove your worth by aiding in the kill.",
    "ObjectivesText": "Slay the Blazing Proto-Dragon.",
    "PortraitGiverName": "Blazing Proto-Dragon",
    "PortraitGiverText": "When a young centaur comes of age, they're often expected to take part in their first proto-drake hunt.",
    "RewardText": "You are a more formidable fighter than I assumed.",
    "Objectives": []
}