{
    "Id": 68639,
    "Title": "Блукаючі Полярні Хижаки",
    "Description": "Вид, який нас відправили вивчати, - це фригідні звірів.\n\nЇхні мисливські угіддя були заплямовані світовими лініями. Таємничі енергії просочуються у воду, рослини... і до здобичі, як-от сліверна.\n\nАле на відміну від інших організмів, фригідні звірі виживають у цьому процесі і отримують від нього енергію.\n\nВони також стають агресивними - що є проблемою. Залучіть кількох, і я зроблю нотатки про їхню силу та агресію. \n\nМій звіт допоможе Кірін Тору вирішити, що з ними робити.",
    "ObjectivesText": "Убити 6 Заражених Фригідних звірів.",
    "AreaDescription": null,
    "PortraitGiverName": null,
    "PortraitGiverText": null,
    "PortraitTurnInName": null,
    "PortraitTurnInText": null,
    "ObjectivesCompletionText": null,
    "CompletionText": null,
    "RewardText": "<Вона робить нотатки у своєму щоденнику.>\n\nТак... Так, це все дуже корисно. Сподіваюся, Кірін Тор зможе використати цю інформацію, щоб допомогти іншим, хто страждає від таємничої хвороби.",
    "Objectives": [
        {
            "Hash": 529428259,
            "Text": "Заражені фригідні звірі убиті"
        }
    ]
}