<?xml version="1.0" encoding="utf-8"?>
<QuestData xmlns:xsi="http://www.w3.org/2001/XMLSchema-instance" xmlns:xsd="http://www.w3.org/2001/XMLSchema" id="29904">
  <Title>Bigger Fish to Fry</Title>
  <Description>I've prepared a team of bright young Pearlfin trainees who need field experience.$B$BTake them northeast, into the Bamboo Wilds, and kill any wildlife that you find.$B$BDon't bring them back until they're fit for battle.</Description>
  <LogDescription>Train the Pearlfin Adepts by killing 24 wildlife in the Bamboo Wilds.</LogDescription>
  <CompletionText>How are those trainees looking?</CompletionText>
  <RewardText>Your trainees returned recently. I could hardly believe my eyes! They did not look like the same jinyu that you left with.$B$BExcellent work, $c. Couldn't have done better myself.</RewardText>
  <Objectives>
    <Objective id="253666">Bamboo Wilds wildlife</Objective>
  </Objectives>
</QuestData>