<?xml version="1.0" encoding="utf-8"?>
<QuestData xmlns:xsi="http://www.w3.org/2001/XMLSchema-instance" xmlns:xsd="http://www.w3.org/2001/XMLSchema" id="11375" type="Heroic">
  <Title>WANTED: Murmur's Whisper</Title>
  <Description>When I'm done speaking, you may not want to take this commission.$B$BI have an eccentric client who specializes in the study of dead realities. It is rumored that the being known as Murmur destroyed the last world from which he was summoned. The professor is interested in examining his 'whisper' as he called it to understand how it is that Murmur accomplished such a feat.$B$BWill you journey to the Shadow Labyrinth within Auchindoun and retrieve it for me?</Description>
  <LogDescription>Wind Trader Zhareem has asked you to obtain Murmur's Whisper. Deliver it to him in Shattrath's Lower City to collect the reward.$B$BThis quest may only be completed on Heroic difficulty.</LogDescription>
  <CompletionText>I'm not even certain what form a whisper is supposed to take in the physical world, but the professor assures me that you'll know it when you see it.$B$BPerhaps it is something akin to the being's voice box?</CompletionText>
  <RewardText>I was worried that you might not return. I trust that you didn't go deaf from fighting Murmur?$B$BHere is your reward. The professor will be pleased no doubt, though I worry what he ultimately wishes to do with this thing.$B$BCome back tomorrow and I will have another request for you to fulfill.</RewardText>
  <Objectives />
</QuestData>