<?xml version="1.0" encoding="utf-8"?>
<QuestData xmlns:xsi="http://www.w3.org/2001/XMLSchema-instance" xmlns:xsd="http://www.w3.org/2001/XMLSchema" id="70154">
  <Title>A Gateway to Somewhere</Title>
  <Description>The enchantment will protect us from the unstable energy contained within.

I will open the way to the nearest stone. 

Once you pass through, stay close. I shall need your assistance when we arrive to power up the device.</Description>
  <LogDescription>Follow Warpcaster Delandra to the Waygate's location.</LogDescription>
  <Objectives>
    <Objective id="430340">Warpcaster Delandra's portal taken</Objective>
    <Objective id="430341">Warpcaster's spire portal taken</Objective>
    <Objective id="430342">Escape with Warpcaster Delandra</Objective>
    <Objective id="430344">Player arrives at Location 1</Objective>
    <Objective id="430366">Player arrives at Location 2</Objective>
    <Objective id="430385">Frenzied Arcane Thirster slain</Objective>
    <Objective id="430399">Player arrives at Location 3</Objective>
  </Objectives>
</QuestData>