<?xml version="1.0" encoding="utf-8"?>
<QuestData xmlns:xsi="http://www.w3.org/2001/XMLSchema-instance" xmlns:xsd="http://www.w3.org/2001/XMLSchema" id="11911" type="Dungeon">
  <Title>Quickening</Title>
  <Description>I've learned more in my short time here than in decades of studies.$b$bThe ancients here are being exposed to incredible levels of arcane energy. It's literally transforming them into something...$b$bI'm confident that there's a final stage in their metamorphosis. Find me some evidence of their final state.</Description>
  <LogDescription>Image of Warmage Kaitlyn in the Nexus wants you to collect 5 Arcane Splinters from Crystalline Protectors.</LogDescription>
  <CompletionText>The Crystalline Ancients... Do they exist?</CompletionText>
  <RewardText>Fascinating!$b$bAnd they're aggressive too, you say. That would suggest that some intelligence is behind this manipulation.$B$BIt may not be natural at all....</RewardText>
  <Objectives />
</QuestData>