<?xml version="1.0" encoding="utf-8"?>
<QuestData xmlns:xsi="http://www.w3.org/2001/XMLSchema-instance" xmlns:xsd="http://www.w3.org/2001/XMLSchema" id="60189">
  <Title>We Strike Now</Title>
  <Description>The time has come. The Wild Hunt has driven the Drust back to their stronghold at the edge of Ardenweald.

Their scouts report that Gorak Zhar herself is among them. This may be our only opportunity to fully purge the minions of Thros from this realm.

Lord Herne awaits your arrival at the battlefront. Go with haste, $n.</Description>
  <LogDescription>Meet Lord Herne outside of Darkreach.</LogDescription>
  <QuestCompletionLog>Meet Lord Herne outside of Darkreach.</QuestCompletionLog>
  <RewardText>Good. You are here.

We are now ready to end the Drust's invasion once and for all.</RewardText>
  <Objectives />
</QuestData>