<?xml version="1.0" encoding="utf-8"?>
<QuestData xmlns:xsi="http://www.w3.org/2001/XMLSchema-instance" xmlns:xsd="http://www.w3.org/2001/XMLSchema" id="9864">
  <Title>The Missing War Party</Title>
  <Description>After the last Murkblood raid, a group of younglings decided to act. We tried to stop them but the rage had taken hold. It has now been one week since we last saw our beloved younglings.$B$BPlease, $r, you must find them! They have just barely reached adolescence. How can they expect to defeat such savages?$B$BThey took the road leading west out of town. Follow that road around and look for signs of our younglings.$B$BAnd $n, avoid Halaa if you value your life. It is a war-zone.</Description>
  <LogDescription>Try and find the missing Garadar war party.</LogDescription>
  <RewardText>I have been told stories of my people. They say that once, we were warriors... </RewardText>
  <Objectives />
</QuestData>