<?xml version="1.0" encoding="utf-8"?>
<QuestData xmlns:xsi="http://www.w3.org/2001/XMLSchema-instance" xmlns:xsd="http://www.w3.org/2001/XMLSchema" id="24947">
  <Title>Momentum</Title>
  <Description>We can't just rest on our laurels here, babe. We've got to keep this momentum going! People are talking about us.$B$BUnfortunately, they're also talking about this air-headed gnome, Kelsey, who's apparently been running jobs right alongside us. If we're going to drive her out of what's rightfully a goblin town, we need to seal the deal here.$B$BWe're going to take care of Gadgetzan's pirate problem for them, for good. Head south to Lost Rigger Cove, I'll meet you there.</Description>
  <LogDescription>Meet Megs Dreadshredder at Lost Rigger Cove.</LogDescription>
  <RewardText>Good thing you're here! I'm gonna need a lot of help if we want to beat these gnomes to the punch.</RewardText>
  <Objectives />
</QuestData>