<?xml version="1.0" encoding="utf-8"?>
<QuestData xmlns:xsi="http://www.w3.org/2001/XMLSchema-instance" xmlns:xsd="http://www.w3.org/2001/XMLSchema" id="25014">
  <Title>Sandscraper's Treasure</Title>
  <Description>Inside this weathered stone chest at the back of Stonescraper's lair, you find a curious artifact.$B$BShaped like a beetle, its surface is a smooth, brilliant blue, lined with gold. It looks mechanical, but unlike anything you've seen crafted by mortal hands, and very old.$B$BMegs will probably be interested in this.</Description>
  <LogDescription>Talk to Megs Dreadshredder.</LogDescription>
  <CompletionText>Find something?</CompletionText>
  <RewardText>You found that in the ogre den? That's...$B$B...nothing to get excited about, I'm sure! I'm sure it's just...a perfectly benign trinket...that I'm going to give you precisely detailed instructions on exactly how to handle.$B$B&lt;Megs drops her voice to a whisper.&gt;$B$BKeep your voice down and don't wave that thing around.</RewardText>
  <Objectives />
</QuestData>