<?xml version="1.0" encoding="utf-8"?>
<QuestData xmlns:xsi="http://www.w3.org/2001/XMLSchema-instance" xmlns:xsd="http://www.w3.org/2001/XMLSchema" id="28839">
  <Title>Magic Prehistoric</Title>
  <Description>The owlbeasts' sacred caves are located to the east. Within several of these caves, you should find totems. I want you to approach these totems and gather whatever essence you can from them. The dreamcatcher should absorb this essence for use within Mazthoril.</Description>
  <PortraitGiverName>Haleh</PortraitGiverName>
  <PortraitGiverText>Their totems are sacred objects. They will defend them ferociously.</PortraitGiverText>
  <PortraitTurnInName>Haleh</PortraitTurnInName>
  <PortraitTurnInText>The ancient magic of the owlbeasts is powerful. But still...</PortraitTurnInText>
  <LogDescription>Obtain the Essence of the Claw-Totem, the Essence of the Life-Totem, and the Essence of the Moon-Totem.</LogDescription>
  <CompletionText>What are you doing, $n? We need that essence.</CompletionText>
  <RewardText>The dreamcatcher is charged.  We are nearly ready to retake Mazthoril.</RewardText>
  <Objectives />
</QuestData>